the_datagarden/__init__.py
the_datagarden/cli.py
the_datagarden/version.py
the_datagarden/abc/__init__.py
the_datagarden/abc/api.py
the_datagarden/abc/authentication.py
the_datagarden/api/__init__.py
the_datagarden/api/authentication/__init__.py
the_datagarden/api/authentication/settings.py
the_datagarden/api/authentication/credentials/__init__.py
the_datagarden/api/authentication/environment/__init__.py
the_datagarden/api/base/__init__.py
the_datagarden/api/regions/__init__.py
the_datagarden/api/regions/continent.py
the_datagarden/api/regions/country.py
the_datagarden/api/regions/base/__init__.py
the_datagarden/api/regions/base/settings.py
the_datagarden/models/__init__.py
the_datagarden/models/geojson.py
the_datagarden/models/regional_data.py
the_datagarden-1.2.6.dist-info/METADATA
the_datagarden-1.2.6.dist-info/WHEEL
the_datagarden-1.2.6.dist-info/entry_points.txt
the_datagarden-1.2.6.dist-info/top_level.txt
the_datagarden-1.2.6.dist-info/RECORD
