Metadata-Version: 2.4
Name: the-datagarden
Version: 1.2.6
Summary: Public data made easy.
Author-email: Maarten de Ruyter <info@the-datagarden.io>
License: MIT
Project-URL: Read the Docs, https://dg-the-datagarden.readthedocs.io/en/stable/
Project-URL: The-DataGarden, https://www.the-datagarden.io/
Project-URL: API documentation, https://www.the-datagarden.io/api-docs
Project-URL: Source, https://github.com/OlivettaDataGarden/dg-the-datagarden
Classifier: Programming Language :: Python :: 3
Classifier: Programming Language :: Python :: 3.10
Classifier: Programming Language :: Python :: 3.11
Classifier: Programming Language :: Python :: 3.12
Classifier: Programming Language :: Python :: 3.13
Classifier: License :: OSI Approved :: MIT License
Classifier: Operating System :: OS Independent
Classifier: Development Status :: 4 - Beta
Classifier: Intended Audience :: Developers
Classifier: Intended Audience :: Financial and Insurance Industry
Classifier: Intended Audience :: Science/Research
Classifier: Intended Audience :: Healthcare Industry
Classifier: Topic :: Scientific/Engineering :: GIS
Classifier: Topic :: Scientific/Engineering :: Artificial Intelligence
Classifier: Topic :: Scientific/Engineering :: Information Analysis
Classifier: Topic :: Scientific/Engineering :: Visualization
Classifier: Topic :: Software Development :: Libraries :: Python Modules
Classifier: Topic :: Utilities
Requires-Python: >=3.10
Requires-Dist: click>=8.1.7
Requires-Dist: pandas>=2.2.3
Requires-Dist: polars>=1.15.0
Requires-Dist: pydantic>=2.9.2
Requires-Dist: pyjwt>=2.10.0
Requires-Dist: python-decouple>=3.8
Requires-Dist: requests>=2.32.3
Requires-Dist: the-datagarden-models>=1.6.3
Provides-Extra: dev
Requires-Dist: mypy>=1.13.0; extra == "dev"
Requires-Dist: pre-commit>=4.0.1; extra == "dev"
Requires-Dist: pytest>=8.3.3; extra == "dev"
Requires-Dist: ruff>=0.7.4; extra == "dev"
Requires-Dist: sphinx>=8.1.3; extra == "dev"
Requires-Dist: types-requests>=2.32.0.20241016; extra == "dev"
